uart_core.v
`timescale 1s/100ms

module uart_core #(
    parameter OVERSAMPLE = 4
)(

    input wire clk,
    input wire rst_n,

    input wire rx,
    output reg tx,
    input wire [9:0] div_int,
    input wire [3:0] div_frac,

    input wire [7:0] tx_byte,
    output reg [7:0] rx_byte,
    input wire tx_valid,
    output wire rx_valid,
    output wire tx_done

);

wire rst_n_sync;

reset_sync #(
    .N_CYCLES (2)
) inst_reset_sync (
    .clk(clk),
    .rst_n_in(rst_n),
    .rst_n_out(rst_n_sync)
);

wire rx_sync;

sync_1bit inst_sync_rx(
    .clk(clk),
    .rst_n(rst_n_sync),
    .i(rx),
    .o(rx_sync)
);

localparam W_OVER = $clog2(OVERSAMPLE + 1);

reg [W_OVER-1:0] tx_over_ctr;
reg [3:0] tx_state;
reg [7:0] tx_shifter;

localparam TX_IDLE = 0;
localparam TX_START = 1;
localparam TX_STOP = 10;

wire clk_en;

clkdiv_frac #(
    .W_DIV_FRAC(4),
    .W_DIV_INT(10)
) inst_clk_div (
    .clk(clk),
    .rst_n(rst_n_sync),
    .en(1'b1),
    .div_frac(div_frac),
    .div_int(div_int),
    .clk_en(clk_en)
);

wire tx_fifo_wen = tx_valid;
wire [7:0] tx_fifo_wdata = tx_byte;
wire tx_fifo_ren = ((!tx_fifo_empty) && clk_en && (tx_state == TX_IDLE || tx_state == TX_STOP));
wire [7:0] tx_fifo_rdata;
wire [1:0] tx_fifo_lvl;
wire tx_fifo_full;
wire tx_fifo_empty;



sync_fifo #(
    .WIDTH (8),
    .DEPTH (2)
) inst_tx_fifo (
    .clk(clk),
    .rst_n(rst_n_sync),
    .w_en(tx_fifo_wen),
    .w_data(tx_fifo_wdata),
    .r_en(tx_fifo_ren),
    .r_data(tx_fifo_rdata),
    .full(tx_fifo_full),
    .empty(tx_fifo_empty),
    .level(tx_fifo_lvl)
);



wire tx_busy = (tx_state != TX_IDLE);
assign tx_done = (tx_state == TX_STOP - 1);


always @(posedge clk or negedge rst_n_sync) begin

    if(!rst_n_sync) begin
        tx <= 1'b1;
        tx_over_ctr <= {W_OVER{1'b0}};
        tx_state <= TX_IDLE;
        tx_shifter <= 8'h0;
        // tx_done <= 1'b0;
    end else begin
        if(clk_en)
            tx_over_ctr <= tx_over_ctr + 1'b1;
        if(clk_en && !tx_over_ctr) begin
            tx_state <= tx_state + 1'b1;

            case(tx_state)

            TX_IDLE: begin
                if(tx_fifo_lvl == 2'd1) begin
                    tx_shifter <= tx_fifo_rdata;
                    tx <= 1'b0;
                end
                else begin
                    tx_over_ctr <= 8'b0;
                    tx_state <= TX_IDLE;
                end
            end

            TX_START: begin
                tx_shifter <= tx_shifter >> 1;
                tx <= tx_shifter[0];
            end

            TX_STOP: begin
                if(tx_valid) begin
                    tx_shifter <= tx_byte;
                    tx <= 1'b0;
                    tx_state <= TX_START;
                end else begin
                    tx_state <= TX_IDLE;
                    tx_over_ctr <= {W_OVER{1'b0}};
                end
            end

            default: begin
                tx_shifter <= tx_shifter >> 1;
                if(tx_state == TX_STOP - 1) begin
                    tx <= 1;
                end else begin
                    tx <= tx_shifter[0];
                end
            end

            endcase
        end
    end


end


reg [W_OVER-1:0] rx_over_ctr;
reg [3:0] rx_state;
reg [7:0] rx_shifter;
reg rxfifo_wen;


wire din = rx_sync;
assign rx_valid = (rx_state == (RX_STOP));

localparam RX_IDLE = 0;
localparam RX_START = 1;
localparam RX_STOP = 10;

always @(posedge clk or negedge rst_n_sync) begin

    if(!rst_n_sync) begin
        rx_over_ctr <= {W_OVER{1'b0}};
        rx_state <= RX_IDLE;
        rx_shifter <= 8'h0;
        rxfifo_wen <= 1'b0;
    end else begin
        rxfifo_wen <= 1'b0;
        if(clk_en)
            rx_over_ctr <= rx_over_ctr + 1'b1;

        if(clk_en && !rx_over_ctr) begin
            rx_state <= rx_state + 1'b1;

            case(rx_state)
                RX_IDLE: begin
                    if(din) begin
                        rx_state <= RX_IDLE;
                        rx_over_ctr <= {W_OVER{1'b0}};
                    end
                end

                RX_START: begin
                    rx_over_ctr <= OVERSAMPLE / 2;
                end

                RX_STOP: begin
                    rxfifo_wen <= din;

                    rx_state <= RX_IDLE;
                    rx_over_ctr <= 0;
                end

                default: begin
                    rx_shifter <= (rx_shifter >> 1) | (din << 7);
                end
            endcase
        end
    end

end


`ifdef COCOTB_SIM
initial begin
  $dumpfile ("uart_test.vcd");
  $dumpvars (0, uart_core);
  #1;
end
`endif

endmodule


module reset_sync #(
    parameter N_CYCLES = 2 // must be >= 2
) (
    input  wire clk,
    input  wire rst_n_in,
    output wire rst_n_out
);

(* keep = 1'b1 *) reg [N_CYCLES-1:0] delay;

always @ (posedge clk or negedge rst_n_in)
    if (!rst_n_in)
        delay <= {N_CYCLES{1'b0}};
    else
        delay <= {delay[N_CYCLES-2:0], 1'b1};

assign rst_n_out = delay[N_CYCLES-1];

endmodule

module sync_1bit #(
    parameter N_STAGES = 2 // Should be >=2
) (
    input wire clk,
    input wire rst_n,
    input wire i,
    output wire o
);

(* keep = 1'b1 *) reg [N_STAGES-1:0] sync_flops;

always @ (posedge clk or negedge rst_n)
    if (!rst_n)
        sync_flops <= {N_STAGES{1'b1}};
    else
        sync_flops <= {sync_flops[N_STAGES-2:0], i};

assign o = sync_flops[N_STAGES-1];

endmodule

module clkdiv_frac #(
    parameter W_DIV_INT = 16,
    parameter W_DIV_FRAC = 8
) (
    input wire                  clk,
    input wire                  rst_n,

    input wire                  en,
    input wire [W_DIV_INT-1:0]  div_int,
    input wire [W_DIV_FRAC-1:0] div_frac,

    output reg                  clk_en
);

reg [W_DIV_INT-1:0]  ctr_int;
reg [W_DIV_FRAC-1:0] ctr_frac;
reg                  frac_carry;

always @ (posedge clk or negedge rst_n) begin
    if (!rst_n) begin
        clk_en <= 1'b0;
        ctr_int <= {W_DIV_INT{1'b0}} | 1'b1;
        ctr_frac <= {W_DIV_FRAC{1'b0}};
        frac_carry <= 1'b0;
    end else if (!en) begin
        // Keep everything clear so that we raise
        // clk_en on the cycle immediately following being enabled
        clk_en <= 1'b0;
        ctr_int <= {W_DIV_INT{1'b0}} | 1'b1;
        ctr_frac <= {W_DIV_FRAC{1'b0}};
        frac_carry <= 1'b0;
    end else begin
        if (ctr_int == 1) begin
            {frac_carry, ctr_frac} <= ctr_frac + div_frac;
            ctr_int <= div_int + frac_carry;
            clk_en <= 1'b1;
        end else begin
            clk_en <= 1'b0;
            ctr_int <= ctr_int - 1'b1;
        end
    end
end

endmodule


module sync_fifo #(
    parameter DEPTH   = 2,
    parameter WIDTH   = 32,
    parameter W_LEVEL = $clog2(DEPTH + 1)
) (
    input wire clk,
    input wire rst_n,

    input  wire [WIDTH-1:0] w_data,
    input  wire             w_en,
    output wire [WIDTH-1:0] r_data,
    input  wire             r_en,

    output wire               full,
    output wire               empty,
    output reg  [W_LEVEL-1:0] level
);

  // valid has an extra bit which should remain constant 0, and mem has an extra
  // entry which is wired through to w_data. This is just to handle the loop
  // boundary condition without tools complaining.
    reg [WIDTH-1:0] mem[0:DEPTH];
    reg [DEPTH:0] valid;

  // ----------------------------------------------------------------------------
  // Control and datapath

    wire push = w_en && !full;
    wire pop = r_en && !empty;

    always @(posedge clk or negedge rst_n) begin
        if (!rst_n) begin
            valid <= {DEPTH + 1{1'b0}};
        end else if (w_en || r_en) begin
      // 2 LUTs 1 FF per flag, all FFs have same clke
            valid <= (valid << push | {{DEPTH - 1{1'b0}}, push}) >> pop;
        end
    end

  // No reset on datapath
  always @(posedge clk) begin : shift_data
    integer i;
    for (i = 0; i < DEPTH; i = i + 1) begin : data_stage
      if (r_en || (w_en && !valid[i] && (i == DEPTH - 1 || !valid[i+1]))) begin
        mem[i] <= valid[i+1] ? mem[i+1] : w_data;
      end
    end
  end

  always @(*) mem[DEPTH] = w_data;
  assign r_data = mem[0];

  // ----------------------------------------------------------------------------
  // Flags

  assign full   = valid[DEPTH-1];
  assign empty  = !valid[0];

  always @(posedge clk or negedge rst_n) begin
    if (!rst_n) begin
      level <= {W_LEVEL{1'b0}};
    end else begin
      level <= level + push - pop;
    end
  end

  // ----------------------------------------------------------------------------
  // Testbench junk vvv

  //synthesis translate_off
  always @(posedge clk) if (w_en && full) $display($time, ": WARNING %m: push on full");
  always @(posedge clk) if (r_en && empty) $display($time, ": WARNING %m: pop on empty");
  //synthesis translate_on


endmodule



// module tb();

//     reg [9:0] div_int;
//     reg [3:0] div_frac;
//     reg clk;
//     reg rx;
//     wire tx;

//     reg rst_n;
//     reg [7:0] tx_byte;
//     wire [7:0] rx_byte;

//     reg tx_valid;
//     wire rx_valid;
//     wire tx_done;

//     initial begin
//         clk <= 0;
//         $dumpfile("uart_test.vcd");
//         $dumpvars(0, tb);
//     end

//     uart_core #(
//         .OVERSAMPLE (4)
//     ) dut (
//         .clk(clk),
//         .rst_n(rst_n),
//         .tx(tx),
//         .tx_byte(tx_byte),
//         .rx(rx),
//         .rx_byte(rx_byte),
//         .div_frac(div_frac),
//         .div_int(div_int),
//         .tx_valid(tx_valid),
//         .tx_done(tx_done),
//         .rx_valid(rx_valid)
//     );

//     always #1 clk <= ~clk;

//     initial begin
//         div_int <= 2;
//         div_frac <= 0;
//         rst_n <= 1;
//         tx_valid <= 0;
//         tx_byte <= 0;
//     end

//     initial begin
//         rx <= 1; 
//         #1 rst_n <= 0;
//         #3 rst_n <= 1;
//         #10 rx <= 1;
//         // #4 tx_valid <= 1;
//         // tx_byte <= 8'b00101010;
//         // #2 tx_valid <= 0;
//         // tx_byte <= 0;
//         #4 rx <= 0;
//         #32 rx <= 1;
//         #32 rx <= 1;
//         #32 rx <= 1;
//         #32 rx <= 1;
//         #32 rx <= 0;
//         #32 rx <= 0;
//         #32 rx <= 0;
//         #32 rx <= 0;
//         #32 rx <= 1;

//         #300 $finish;
//     end




// endmodule

uart_test.vcd
$date
	Sun Mar 26 16:15:32 2023
$end
$version
	Icarus Verilog
$end
$timescale
	1ps
$end
$scope module uart_core $end
$var wire 1 ! clk $end
$var wire 1 " din $end
$var wire 4 # div_frac [3:0] $end
$var wire 10 $ div_int [9:0] $end
$var wire 1 % rst_n $end
$var wire 1 & rx $end
$var wire 8 ' tx_byte [7:0] $end
$var wire 1 ( tx_fifo_ren $end
$var wire 8 ) tx_fifo_wdata [7:0] $end
$var wire 1 * tx_fifo_wen $end
$var wire 1 + tx_valid $end
$var wire 8 , tx_fifo_rdata [7:0] $end
$var wire 2 - tx_fifo_lvl [1:0] $end
$var wire 1 . tx_fifo_full $end
$var wire 1 / tx_fifo_empty $end
$var wire 1 0 tx_done $end
$var wire 1 1 tx_busy $end
$var wire 1 2 rx_valid $end
$var wire 1 3 rx_sync $end
$var wire 1 4 rst_n_sync $end
$var wire 1 5 clk_en $end
$var reg 8 6 rx_byte [7:0] $end
$var reg 3 7 rx_over_ctr [2:0] $end
$var reg 8 8 rx_shifter [7:0] $end
$var reg 4 9 rx_state [3:0] $end
$var reg 1 : rxfifo_wen $end
$var reg 1 ; tx $end
$var reg 3 < tx_over_ctr [2:0] $end
$var reg 8 = tx_shifter [7:0] $end
$var reg 4 > tx_state [3:0] $end
$scope module inst_clk_div $end
$var wire 1 ! clk $end
$var wire 4 ? div_frac [3:0] $end
$var wire 10 @ div_int [9:0] $end
$var wire 1 A en $end
$var wire 1 4 rst_n $end
$var reg 1 5 clk_en $end
$var reg 4 B ctr_frac [3:0] $end
$var reg 10 C ctr_int [9:0] $end
$var reg 1 D frac_carry $end
$upscope $end
$scope module inst_reset_sync $end
$var wire 1 ! clk $end
$var wire 1 % rst_n_in $end
$var wire 1 4 rst_n_out $end
$var reg 2 E delay [1:0] $end
$upscope $end
$scope module inst_sync_rx $end
$var wire 1 ! clk $end
$var wire 1 & i $end
$var wire 1 4 rst_n $end
$var wire 1 3 o $end
$var reg 2 F sync_flops [1:0] $end
$upscope $end
$scope module inst_tx_fifo $end
$var wire 1 ! clk $end
$var wire 1 G pop $end
$var wire 1 H push $end
$var wire 8 I r_data [7:0] $end
$var wire 1 ( r_en $end
$var wire 1 4 rst_n $end
$var wire 8 J w_data [7:0] $end
$var wire 1 * w_en $end
$var wire 1 . full $end
$var wire 1 / empty $end
$var reg 2 K level [1:0] $end
$var reg 3 L valid [2:0] $end
$scope begin shift_data $end
$var integer 32 M i [31:0] $end
$scope begin data_stage $end
$upscope $end
$upscope $end
$upscope $end
$upscope $end
$enddefinitions $end
#0
$dumpvars
b10 M
b0 L
b0 K
bz J
bx I
0H
0G
b11 F
b0 E
0D
b1 C
b0 B
1A
b10 @
b0 ?
b0 >
b0 =
b0 <
1;
0:
b0 9
b0 8
b0 7
bx 6
05
04
13
02
01
00
1/
0.
b0 -
bx ,
0+
0*
bz )
0(
bz '
1&
0%
b10 $
b0 #
1"
1!
$end
#50000
0!
#100000
1%
b10 M
1!
#150000
0!
#200000
b1 E
b10 M
1!
#250000
0!
#300000
14
b11 E
b10 M
1!
#350000
0!
#400000
15
b10 C
b10 M
1!
#450000
1H
b11110000 )
b11110000 J
b11110000 '
1*
1+
0!
#500000
0/
b1 C
05
b1 L
b1 -
b1 K
01
b0 >
b0 <
b0 9
b0 7
b11110000 ,
b11110000 I
b10 M
1!
#550000
0H
0*
0+
0!
#600000
1G
1(
15
b10 C
b10 M
1!
#650000
0!
#700000
0G
0(
1/
b1 C
05
b0 L
b0 -
b0 K
0;
b11110000 =
11
b1 >
b1 <
b0 9
b0 7
b10 M
1!
#750000
0!
#800000
15
b10 C
b10 M
1!
#850000
0!
#900000
b1 C
05
b10 <
b0 9
b0 7
b10 M
1!
#950000
0!
#1000000
15
b10 C
b10 M
1!
#1050000
0!
#1100000
b1 C
05
b11 <
b0 9
b0 7
b10 M
1!
#1150000
0!
#1200000
15
b10 C
b10 M
1!
#1250000
0!
#1300000
b1 C
05
b100 <
b0 9
b0 7
b10 M
1!
#1350000
0!
#1400000
15
b10 C
b10 M
1!
#1450000
0!
#1500000
b1 C
05
b101 <
b0 9
b0 7
b10 M
1!
#1550000
0!
#1600000
15
b10 C
b10 M
1!
#1650000
0!
#1700000
b1 C
05
b110 <
b0 9
b0 7
b10 M
1!
#1750000
0!
#1800000
15
b10 C
b10 M
1!
#1850000
0!
#1900000
b1 C
05
b111 <
b0 9
b0 7
b10 M
1!
#1950000
0!
#2000000
15
b10 C
b10 M
1!
#2050000
0!
#2100000
b1 C
05
b0 <
b0 9
b0 7
b10 M
1!
#2150000
0!
#2200000
15
b10 C
b10 M
1!
#2250000
0!
#2300000
b1 C
05
b1111000 =
b10 >
b1 <
b0 9
b0 7
b10 M
1!
#2350000
0!
#2400000
15
b10 C
b10 M
1!
#2450000
0!
#2500000
b1 C
05
b10 <
b0 9
b0 7
b10 M
1!
#2550000
0!
#2600000
15
b10 C
b10 M
1!
#2650000
0!
#2700000
b1 C
05
b11 <
b0 9
b0 7
b10 M
1!
#2750000
0!
#2800000
15
b10 C
b10 M
1!
#2850000
0!
#2900000
b1 C
05
b100 <
b0 9
b0 7
b10 M
1!
#2950000
0!
#3000000
15
b10 C
b10 M
1!
#3050000
0!
#3100000
b1 C
05
b101 <
b0 9
b0 7
b10 M
1!
#3150000
0!
#3200000
15
b10 C
b10 M
1!
#3250000
0!
#3300000
b1 C
05
b110 <
b0 9
b0 7
b10 M
1!
#3350000
0!
#3400000
15
b10 C
b10 M
1!
#3450000
0!
#3500000
b1 C
05
b111 <
b0 9
b0 7
b10 M
1!
#3550000
0!
#3600000
15
b10 C
b10 M
1!
#3650000
0!
#3700000
b1 C
05
b0 <
b0 9
b0 7
b10 M
1!
#3750000
0!
#3800000
15
b10 C
b10 M
1!
#3850000
0!
#3900000
b1 C
05
b111100 =
b11 >
b1 <
b0 9
b0 7
b10 M
1!
#3950000
0!
#4000000
15
b10 C
b10 M
1!
#4050000
0!
#4100000
b1 C
05
b10 <
b0 9
b0 7
b10 M
1!
#4150000
0!
#4200000
15
b10 C
b10 M
1!
#4250000
0!
#4300000
b1 C
05
b11 <
b0 9
b0 7
b10 M
1!
#4350000
0!
#4400000
15
b10 C
b10 M
1!
#4450000
0!
#4500000
b1 C
05
b100 <
b0 9
b0 7
b10 M
1!
#4550000
0!
#4600000
15
b10 C
b10 M
1!
#4650000
0!
#4700000
b1 C
05
b101 <
b0 9
b0 7
b10 M
1!
#4750000
0!
#4800000
15
b10 C
b10 M
1!
#4850000
0!
#4900000
b1 C
05
b110 <
b0 9
b0 7
b10 M
1!
#4950000
0!
#5000000
15
b10 C
b10 M
1!
#5050000
0!
#5100000
b1 C
05
b111 <
b0 9
b0 7
b10 M
1!
#5150000
0!
#5200000
15
b10 C
b10 M
1!
#5250000
0!
#5300000
b1 C
05
b0 <
b0 9
b0 7
b10 M
1!
#5350000
0!
#5400000
15
b10 C
b10 M
1!
#5450000
0!
#5500000
b1 C
05
b11110 =
b100 >
b1 <
b0 9
b0 7
b10 M
1!
#5550000
0!
#5600000
15
b10 C
b10 M
1!
#5650000
0!
#5700000
b1 C
05
b10 <
b0 9
b0 7
b10 M
1!
#5750000
0!
#5800000
15
b10 C
b10 M
1!
#5850000
0!
#5900000
b1 C
05
b11 <
b0 9
b0 7
b10 M
1!
#5950000
0!
#6000000
15
b10 C
b10 M
1!
#6050000
0!
#6100000
b1 C
05
b100 <
b0 9
b0 7
b10 M
1!
#6150000
0!
#6200000
15
b10 C
b10 M
1!
#6250000
0!
#6300000
b1 C
05
b101 <
b0 9
b0 7
b10 M
1!
#6350000
0!
#6400000
15
b10 C
b10 M
1!
#6450000
0!
#6500000
b1 C
05
b110 <
b0 9
b0 7
b10 M
1!
#6550000
0!
#6600000
15
b10 C
b10 M
1!
#6650000
0!
#6700000
b1 C
05
b111 <
b0 9
b0 7
b10 M
1!
#6750000
0!
#6800000
15
b10 C
b10 M
1!
#6850000
0!
#6900000
b1 C
05
b0 <
b0 9
b0 7
b10 M
1!
#6950000
0!
#7000000
15
b10 C
b10 M
1!
#7050000
0!
#7100000
b1 C
05
b1111 =
b101 >
b1 <
b0 9
b0 7
b10 M
1!
#7150000
0!
#7200000
15
b10 C
b10 M
1!
#7250000
0!
#7300000
b1 C
05
b10 <
b0 9
b0 7
b10 M
1!
#7350000
0!
#7400000
15
b10 C
b10 M
1!
#7450000
0!
#7500000
b1 C
05
b11 <
b0 9
b0 7
b10 M
1!
#7550000
0!
#7600000
15
b10 C
b10 M
1!
#7650000
0!
#7700000
b1 C
05
b100 <
b0 9
b0 7
b10 M
1!
#7750000
0!
#7800000
15
b10 C
b10 M
1!
#7850000
0!
#7900000
b1 C
05
b101 <
b0 9
b0 7
b10 M
1!
#7950000
0!
#8000000
15
b10 C
b10 M
1!
#8050000
0!
#8100000
b1 C
05
b110 <
b0 9
b0 7
b10 M
1!
#8150000
0!
#8200000
15
b10 C
b10 M
1!
#8250000
0!
#8300000
b1 C
05
b111 <
b0 9
b0 7
b10 M
1!
#8350000
0!
#8400000
15
b10 C
b10 M
1!
#8450000
0!
#8500000
b1 C
05
b0 <
b0 9
b0 7
b10 M
1!
#8550000
0!
#8600000
15
b10 C
b10 M
1!
#8650000
0!
#8700000
b1 C
05
1;
b111 =
b110 >
b1 <
b0 9
b0 7
b10 M
1!
#8750000
0!
#8800000
15
b10 C
b10 M
1!
#8850000
0!
#8900000
b1 C
05
b10 <
b0 9
b0 7
b10 M
1!
#8950000
0!
#9000000
15
b10 C
b10 M
1!
#9050000
0!
#9100000
b1 C
05
b11 <
b0 9
b0 7
b10 M
1!
#9150000
0!
#9200000
15
b10 C
b10 M
1!
#9250000
0!
#9300000
b1 C
05
b100 <
b0 9
b0 7
b10 M
1!
#9350000
0!
#9400000
15
b10 C
b10 M
1!
#9450000
0!
#9500000
b1 C
05
b101 <
b0 9
b0 7
b10 M
1!
#9550000
0!
#9600000
15
b10 C
b10 M
1!
#9650000
0!
#9700000
b1 C
05
b110 <
b0 9
b0 7
b10 M
1!
#9750000
0!
#9800000
15
b10 C
b10 M
1!
#9850000
0!
#9900000
b1 C
05
b111 <
b0 9
b0 7
b10 M
1!
#9950000
0!
#10000000
15
b10 C
b10 M
1!
#10050000
0!
#10100000
b1 C
05
b0 <
b0 9
b0 7
b10 M
1!
#10150000
0!
#10200000
15
b10 C
b10 M
1!
#10250000
0!
#10300000
b1 C
05
b11 =
b111 >
b1 <
b0 9
b0 7
b10 M
1!
#10350000
0!
#10400000
15
b10 C
b10 M
1!
#10450000
0!
#10500000
b1 C
05
b10 <
b0 9
b0 7
b10 M
1!
#10550000
0!
#10600000
15
b10 C
b10 M
1!
#10650000
0!
#10700000
b1 C
05
b11 <
b0 9
b0 7
b10 M
1!
#10750000
0!
#10800000
15
b10 C
b10 M
1!
#10850000
0!
#10900000
b1 C
05
b100 <
b0 9
b0 7
b10 M
1!
#10950000
0!
#11000000
15
b10 C
b10 M
1!
#11050000
0!
#11100000
b1 C
05
b101 <
b0 9
b0 7
b10 M
1!
#11150000
0!
#11200000
15
b10 C
b10 M
1!
#11250000
0!
#11300000
b1 C
05
b110 <
b0 9
b0 7
b10 M
1!
#11350000
0!
#11400000
15
b10 C
b10 M
1!
#11450000
0!
#11500000
b1 C
05
b111 <
b0 9
b0 7
b10 M
1!
#11550000
0!
#11600000
15
b10 C
b10 M
1!
#11650000
0!
#11700000
b1 C
05
b0 <
b0 9
b0 7
b10 M
1!
#11750000
0!
#11800000
15
b10 C
b10 M
1!
#11850000
0!
#11900000
b1 C
05
b1 =
b1000 >
b1 <
b0 9
b0 7
b10 M
1!
#11950000
0!
#12000000
15
b10 C
b10 M
1!
#12050000
0!
#12100000
b1 C
05
b10 <
b0 9
b0 7
b10 M
1!
#12150000
0!
#12200000
15
b10 C
b10 M
1!
#12250000
0!
#12300000
b1 C
05
b11 <
b0 9
b0 7
b10 M
1!
#12350000
0!
#12400000
15
b10 C
b10 M
1!
#12450000
0!
#12500000
b1 C
05
b100 <
b0 9
b0 7
b10 M
1!
#12550000
0!
#12600000
15
b10 C
b10 M
1!
#12650000
0!
#12700000
b1 C
05
b101 <
b0 9
b0 7
b10 M
1!
#12750000
0!
#12800000
15
b10 C
b10 M
1!
#12850000
0!
#12900000
b1 C
05
b110 <
b0 9
b0 7
b10 M
1!
#12950000
0!
#13000000
15
b10 C
b10 M
1!
#13050000
0!
#13100000
b1 C
05
b111 <
b0 9
b0 7
b10 M
1!
#13150000
0!
#13200000
15
b10 C
b10 M
1!
#13250000
0!
#13300000
b1 C
05
b0 <
b0 9
b0 7
b10 M
1!
#13350000
0!
#13400000
15
b10 C
b10 M
1!
#13450000
0!
#13500000
b1 C
05
b0 =
10
b1001 >
b1 <
b0 9
b0 7
b10 M
1!
#13550000
0!
#13600000
15
b10 C
b10 M
1!
#13650000
0!
#13700000
b1 C
05
b10 <
b0 9
b0 7
b10 M
1!
#13750000
0!
#13800000
15
b10 C
b10 M
1!
#13850000
0!
#13900000
b1 C
05
b11 <
b0 9
b0 7
b10 M
1!
#13950000
0!
#14000000
15
b10 C
b10 M
1!
#14050000
0!
#14100000
b1 C
05
b100 <
b0 9
b0 7
b10 M
1!
#14150000
0!
#14200000
15
b10 C
b10 M
1!
#14250000
0!
#14300000
b1 C
05
b101 <
b0 9
b0 7
b10 M
1!
#14350000
0!
#14400000
15
b10 C
b10 M
1!
#14450000
0!
#14500000
b1 C
05
b110 <
b0 9
b0 7
b10 M
1!
#14550000
0!
#14600000
15
b10 C
b10 M
1!
#14650000
0!
#14700000
b1 C
05
b111 <
b0 9
b0 7
b10 M
1!
#14750000
0!
#14800000
15
b10 C
b10 M
1!
#14850000
0!
#14900000
b1 C
05
b0 <
b0 9
b0 7
b10 M
1!
#14950000
0!
#15000000
15
b10 C
b10 M
1!
#15050000
0!
#15100000
b1 C
05
00
b1010 >
b1 <
b0 9
b0 7
b10 M
1!
#15150000
0!
#15200000
15
b10 C
b10 M
1!
#15250000
0!
#15300000
b1 C
05
b10 <
b0 9
b0 7
b10 M
1!
#15350000
0!
#15400000
15
b10 C
b10 M
1!
#15450000
0!
#15500000
b1 C
05
b11 <
b0 9
b0 7
b10 M
1!
#15550000
0!
#15600000
15
b10 C
b10 M
1!
#15650000
0!
#15700000
b1 C
05
b100 <
b0 9
b0 7
b10 M
1!
#15750000
0!
#15800000
15
b10 C
b10 M
1!
#15850000
0!
#15900000
b1 C
05
b101 <
b0 9
b0 7
b10 M
1!
#15950000
0!
#16000000
15
b10 C
b10 M
1!
#16050000
0!
#16100000
b1 C
05
b110 <
b0 9
b0 7
b10 M
1!
#16150000
0!
#16200000
15
b10 C
b10 M
1!
#16250000
0!
#16300000
b1 C
05
b111 <
b0 9
b0 7
b10 M
1!
#16350000
0!
#16400000
15
b10 C
b10 M
1!
#16450000
0!
#16500000
b1 C
05
b0 <
b0 9
b0 7
b10 M
1!
#16550000
0!
#16600000
15
b10 C
b10 M
1!
#16650000
0!
#16700000
b1 C
05
01
b0 >
b0 <
b0 9
b0 7
b10 M
1!
#16750000
0!
#16800000
15
b10 C
b10 M
1!
#16850000
0!
#16900000
b1 C
05
01
b0 >
b0 <
b0 9
b0 7
b10 M
1!
#16950000
0!
#17000000
15
b10 C
b10 M
1!
#17050000
0!
#17100000
b1 C
05
01
b0 >
b0 <
b0 9
b0 7
b10 M
1!
#17150000
0!
#17200000
15
b10 C
b10 M
1!
#17250000
0!
#17300000
b1 C
05
01
b0 >
b0 <
b0 9
b0 7
b10 M
1!
#17350000
0!
#17400000
15
b10 C
b10 M
1!
#17450000
0!
#17500000
b1 C
05
01
b0 >
b0 <
b0 9
b0 7
b10 M
1!
