uart_core.v
`timescale 1s/100ms

module uart_core #(
    parameter OVERSAMPLE = 4
)(

    input wire clk,
    input wire rst_n,

    input wire rx,
    output reg tx,
    input wire [9:0] div_int,
    input wire [3:0] div_frac,

    input wire [7:0] tx_byte,
    output [7:0] rx_byte,
    input wire tx_valid,
    output wire rx_valid,
    output wire tx_done,
    input wire rxfifo_ren_ext,
    output wire rx_irq


);

wire rst_n_sync;

reset_sync #(
    .N_CYCLES (2)
) inst_reset_sync (
    .clk(clk),
    .rst_n_in(rst_n),
    .rst_n_out(rst_n_sync)
);

wire rx_sync;

sync_1bit inst_sync_rx(
    .clk(clk),
    .rst_n(rst_n_sync),
    .i(rx),
    .o(rx_sync)
);

localparam W_OVER = $clog2(OVERSAMPLE);

reg [W_OVER-1:0] tx_over_ctr;
reg [3:0] tx_state;
reg [7:0] tx_shifter;

localparam TX_IDLE = 0;
localparam TX_START = 1;
localparam TX_STOP = 10;

wire clk_en;

clkdiv_frac #(
    .W_DIV_FRAC(4),
    .W_DIV_INT(10)
) inst_clk_div (
    .clk(clk),
    .rst_n(rst_n_sync),
    .en(1'b1),
    .div_frac(div_frac),
    .div_int(div_int),
    .clk_en(clk_en)
);

wire tx_fifo_wen = tx_valid;
wire [7:0] tx_fifo_wdata = tx_byte;
wire tx_fifo_ren = ((!tx_fifo_empty) && clk_en && (tx_state == TX_IDLE || tx_state == TX_STOP)
                    && (!tx_over_ctr));
wire [7:0] tx_fifo_rdata;
wire [2:0] tx_fifo_lvl;
wire tx_fifo_full;
wire tx_fifo_empty;



sync_fifo #(
    .WIDTH (8),
    .DEPTH (5)
) inst_tx_fifo (
    .clk(clk),
    .rst_n(rst_n_sync),
    .w_en(tx_fifo_wen),
    .w_data(tx_fifo_wdata),
    .r_en(tx_fifo_ren),
    .r_data(tx_fifo_rdata),
    .full(tx_fifo_full),
    .empty(tx_fifo_empty),
    .level(tx_fifo_lvl)
);



wire tx_busy = (tx_state != TX_IDLE);
assign tx_done = (tx_state == TX_STOP - 1);


always @(posedge clk or negedge rst_n_sync) begin

    if(!rst_n_sync) begin
        tx <= 1'b1;
        tx_over_ctr <= {W_OVER{1'b0}};
        tx_state <= TX_IDLE;
        tx_shifter <= 8'h0;
        // tx_done <= 1'b0;
    end else begin
        if(clk_en)
            tx_over_ctr <= tx_over_ctr + 1'b1;
        if(clk_en && !tx_over_ctr) begin
            tx_state <= tx_state + 1'b1;

            case(tx_state)

            TX_IDLE: begin
                if(!tx_fifo_empty) begin
                    tx_shifter <= tx_fifo_rdata;
                    tx <= 1'b0;
                end
                else begin
                    tx_over_ctr <= 8'b0;
                    tx_state <= TX_IDLE;
                end
            end

            TX_START: begin
                tx_shifter <= tx_shifter >> 1;
                tx <= tx_shifter[0];
            end

            TX_STOP: begin
                if(!tx_fifo_empty) begin
                    tx_shifter <= tx_fifo_rdata;
                    tx <= 1'b0;
                    tx_state <= TX_START;
                end else begin
                    tx_state <= TX_IDLE;
                    tx_over_ctr <= {W_OVER{1'b0}};
                end
            end

            default: begin
                tx_shifter <= tx_shifter >> 1;
                if(tx_state == TX_STOP - 1) begin
                    tx <= 1;
                end else begin
                    tx <= tx_shifter[0];
                end
            end

            endcase
        end
    end


end


reg [W_OVER-1:0] rx_over_ctr;
reg [3:0] rx_state;
reg [7:0] rx_shifter;
reg rxfifo_wen;


wire din = rx_sync;
assign rx_valid = (rx_state == (RX_STOP));

wire rx_fifo_full;
wire [2:0] rx_fifo_lvl;
wire rx_fifo_empty;

localparam RX_IDLE = 0;
localparam RX_START = 1;
localparam RX_STOP = 10;

sync_fifo #(
    .WIDTH (8),
    .DEPTH (5)
) inst_rx_fifo (
    .clk(clk),
    .rst_n(rst_n_sync),
    .w_en(rxfifo_wen),
    .w_data(rx_shifter),
    .r_en(rxfifo_ren_ext),
    .r_data(rx_byte),
    .full(rx_fifo_full),
    .empty(rx_fifo_empty),
    .level(rx_fifo_lvl)
);

assign rx_irq = !rx_fifo_empty;

always @(posedge clk or negedge rst_n_sync) begin

    if(!rst_n_sync) begin
        rx_over_ctr <= {W_OVER{1'b0}};
        rx_state <= RX_IDLE;
        rx_shifter <= 8'h0;
        rxfifo_wen <= 1'b0;
    end else begin
        rxfifo_wen <= 1'b0;
        if(clk_en)
            rx_over_ctr <= rx_over_ctr + 1'b1;

        if(clk_en && !rx_over_ctr) begin
            rx_state <= rx_state + 1'b1;

            case(rx_state)
                RX_IDLE: begin
                    if(din) begin
                        rx_state <= RX_IDLE;
                        rx_over_ctr <= {W_OVER{1'b0}};
                    end
                end

                RX_START: begin
                    rx_over_ctr <= OVERSAMPLE / 2;
                end

                RX_STOP: begin
                    rxfifo_wen <= din;

                    rx_state <= RX_IDLE;
                    rx_over_ctr <= 0;
                end

                default: begin
                    rx_shifter <= (rx_shifter >> 1) | (din << 7);
                end
            endcase
        end
    end

end


// `ifdef COCOTB_SIM
// initial begin
//   $dumpfile ("uart_test.vcd");
//   $dumpvars (0, uart_core);
//   #1;
// end
// `endif

endmodule


module reset_sync #(
    parameter N_CYCLES = 2 // must be >= 2
) (
    input  wire clk,
    input  wire rst_n_in,
    output wire rst_n_out
);

(* keep = 1'b1 *) reg [N_CYCLES-1:0] delay;

always @ (posedge clk or negedge rst_n_in)
    if (!rst_n_in)
        delay <= {N_CYCLES{1'b0}};
    else
        delay <= {delay[N_CYCLES-2:0], 1'b1};

assign rst_n_out = delay[N_CYCLES-1];

endmodule

module sync_1bit #(
    parameter N_STAGES = 2 // Should be >=2
) (
    input wire clk,
    input wire rst_n,
    input wire i,
    output wire o
);

(* keep = 1'b1 *) reg [N_STAGES-1:0] sync_flops;

always @ (posedge clk or negedge rst_n)
    if (!rst_n)
        sync_flops <= {N_STAGES{1'b1}};
    else
        sync_flops <= {sync_flops[N_STAGES-2:0], i};

assign o = sync_flops[N_STAGES-1];

endmodule

module clkdiv_frac #(
    parameter W_DIV_INT = 16,
    parameter W_DIV_FRAC = 8
) (
    input wire                  clk,
    input wire                  rst_n,

    input wire                  en,
    input wire [W_DIV_INT-1:0]  div_int,
    input wire [W_DIV_FRAC-1:0] div_frac,

    output reg                  clk_en
);

reg [W_DIV_INT-1:0]  ctr_int;
reg [W_DIV_FRAC-1:0] ctr_frac;
reg                  frac_carry;

always @ (posedge clk or negedge rst_n) begin
    if (!rst_n) begin
        clk_en <= 1'b0;
        ctr_int <= {W_DIV_INT{1'b0}} | 1'b1;
        ctr_frac <= {W_DIV_FRAC{1'b0}};
        frac_carry <= 1'b0;
    end else if (!en) begin
        // Keep everything clear so that we raise
        // clk_en on the cycle immediately following being enabled
        clk_en <= 1'b0;
        ctr_int <= {W_DIV_INT{1'b0}} | 1'b1;
        ctr_frac <= {W_DIV_FRAC{1'b0}};
        frac_carry <= 1'b0;
    end else begin
        if (ctr_int == 1) begin
            {frac_carry, ctr_frac} <= ctr_frac + div_frac;
            ctr_int <= div_int + frac_carry;
            clk_en <= 1'b1;
        end else begin
            clk_en <= 1'b0;
            ctr_int <= ctr_int - 1'b1;
        end
    end
end

endmodule


module sync_fifo #(
    parameter DEPTH   = 2,
    parameter WIDTH   = 32,
    parameter W_LEVEL = $clog2(DEPTH + 1)
) (
    input wire clk,
    input wire rst_n,

    input  wire [WIDTH-1:0] w_data,
    input  wire             w_en,
    output wire [WIDTH-1:0] r_data,
    input  wire             r_en,

    output wire               full,
    output wire               empty,
    output reg  [W_LEVEL-1:0] level
);

  // valid has an extra bit which should remain constant 0, and mem has an extra
  // entry which is wired through to w_data. This is just to handle the loop
  // boundary condition without tools complaining.
    reg [WIDTH-1:0] mem[0:DEPTH];
    reg [DEPTH:0] valid;

  // ----------------------------------------------------------------------------
  // Control and datapath

    wire push = w_en && !full;
    wire pop = r_en && !empty;

    always @(posedge clk or negedge rst_n) begin
        if (!rst_n) begin
            valid <= {DEPTH + 1{1'b0}};
        end else if (w_en || r_en) begin
      // 2 LUTs 1 FF per flag, all FFs have same clke
            valid <= (valid << push | {{DEPTH - 1{1'b0}}, push}) >> pop;
        end
    end

  // No reset on datapath
  always @(posedge clk) begin : shift_data
    integer i;
    for (i = 0; i < DEPTH; i = i + 1) begin : data_stage
      if (r_en || (w_en && !valid[i] && (i == DEPTH - 1 || !valid[i+1]))) begin
        mem[i] <= valid[i+1] ? mem[i+1] : w_data;
      end
    end
  end

  always @(*) mem[DEPTH] = w_data;
  assign r_data = mem[0];

  // ----------------------------------------------------------------------------
  // Flags

  assign full   = valid[DEPTH-1];
  assign empty  = !valid[0];

  always @(posedge clk or negedge rst_n) begin
    if (!rst_n) begin
      level <= {W_LEVEL{1'b0}};
    end else begin
      level <= level + push - pop;
    end
  end

  // ----------------------------------------------------------------------------
  // Testbench junk vvv

  //synthesis translate_off
  always @(posedge clk) if (w_en && full) $display($time, ": WARNING %m: push on full");
  always @(posedge clk) if (r_en && empty) $display($time, ": WARNING %m: pop on empty");
  //synthesis translate_on


endmodule

uart_regs.v
`include "uart_core.v"

module uart_regs #(

    parameter W_REG = 32

)(
    input wire clk,
    input wire rst_n,

    input wire rx,
    input wire tx,
    input wire [9:0] div_int,
    input wire [3:0] div_frac,

    output wire [W_REG-1:0] Reg1,
    output wire [W_REG-1:0] Reg2,
    output wire [W_REG-1:0] Reg3,
    output wire [W_REG-1:0] Reg4,
    output wire [W_REG-1:0] Reg5,
    output wire [W_REG-1:0] Reg6,
    output wire [W_REG-1:0] Reg7,
    output wire [W_REG-1:0] Reg8
);

localparam REG_ADDR = $clog2(8);

reg [W_REG-1:0] mem [0:7];

reg [REG_ADDR-1:0] addr;

reg [3:0] state;

wire rst_n_sync;

localparam IDLE = 0;
localparam READ_REG = 1;
localparam WRITE_REG = 2;
localparam TX_BYTE = 3;
localparam RX_BYTE = 4;
localparam WRITE_COMPLETE = 5;
localparam READ_COMPLETE  = 6;
localparam RESOLVE = 7;

wire rx_irq;
reg rx_ren;
wire rx_valid;
wire tx_done;
reg [7:0] tx_byte;
wire [7:0] rx_byte;
reg tx_valid;

wire read_reg = (rx_byte[7:5] == 3'b101);

reg [2:0] cnt_byte;
reg [31:0] temp_wdata;



uart_core #(
    .OVERSAMPLE(4)
) inst_uart (
    .clk(clk),
    .rst_n(rst_n),
    .tx(tx),
    .rx(rx),
    .div_int(div_int),
    .div_frac(div_frac),
    .tx_byte(tx_byte),
    .rx_byte(rx_byte),
    .tx_valid(tx_valid),
    .rx_valid(rx_valid),
    .tx_done(tx_done),
    .rxfifo_ren_ext(rx_ren),
    .rx_irq(rx_irq)
);

reset_sync #(
    .N_CYCLES (2)
) inst_reset_sync (
    .clk(clk),
    .rst_n_in(rst_n),
    .rst_n_out(rst_n_sync)
);

always @(posedge clk or negedge rst_n_sync) begin

    if(!rst_n_sync) begin
        state <= IDLE;
        rx_ren <= 1'b0;
        tx_valid <= 1'b0;
        tx_byte <= 0;
        addr <= 0;
        // mem <= 0;
        cnt_byte <= 2'b0;
        temp_wdata <= 0;
    end else begin

        case(state)

            IDLE: begin
                tx_valid <= 1'b0;
                if(rx_irq) begin
                    rx_ren <= 1'b1;
                    addr <= rx_byte[2:0];
                    if(read_reg) begin
                        state <= READ_REG;
                    end
                    else begin
                        state <= WRITE_REG;
                        temp_wdata <= 32'b0;
                    end
                end
                else begin
                    state <= IDLE;
                end
            end

            READ_REG: begin
                rx_ren <= 1'b0;
                cnt_byte <= cnt_byte + 1'b1;
                tx_valid <= 1'b1;
                case(cnt_byte)
                    0: tx_byte <= mem[cnt_byte][7:0];
                    1: tx_byte <= mem[cnt_byte][15:8];
                    2: tx_byte <= mem[cnt_byte][23:16];
                    3: tx_byte <= mem[cnt_byte][31:24];

                    default:
                        tx_byte <= tx_byte;
                endcase

                if(cnt_byte == 3'd3) begin
                    state <= IDLE;
                    // tx_valid <= 1'b0;
                    cnt_byte <= 3'd0;
                end
                else begin
                    state <= READ_REG;
                end
            end

            WRITE_REG: begin
                if(cnt_byte != 3'd3) begin
                    if(rx_irq) begin
                        rx_ren <= 1;
                        temp_wdata <= temp_wdata | (rx_byte << (1 << cnt_byte));
                        cnt_byte <= cnt_byte + 1;
                    end else begin
                        rx_ren <= 0;
                    end
                    state <= WRITE_REG;
                end else begin
                    rx_ren <= 1'b0;
                    temp_wdata <= 0;
                    cnt_byte <= 0;
                    state <= IDLE;
                end
            end

            default: begin
            end

        endcase

    end


end


`ifdef COCOTB_SIM
initial begin
  $dumpfile ("uart_test.vcd");
  $dumpvars (0, uart_regs);
  #1;
end

initial begin
    integer i;
    for(i = 0; i < 8; i =i+1) begin
        mem[i] = 32'h12345678;
    end
end
`endif


endmodule

uart_test.vcd
$date
	Sun Mar 26 23:28:10 2023
$end
$version
	Icarus Verilog
$end
$timescale
	1ps
$end
$scope module uart_regs $end
$var wire 32 ! Reg1 [31:0] $end
$var wire 32 " Reg2 [31:0] $end
$var wire 32 # Reg3 [31:0] $end
$var wire 32 $ Reg4 [31:0] $end
$var wire 32 % Reg5 [31:0] $end
$var wire 32 & Reg6 [31:0] $end
$var wire 32 ' Reg7 [31:0] $end
$var wire 32 ( Reg8 [31:0] $end
$var wire 1 ) clk $end
$var wire 4 * div_frac [3:0] $end
$var wire 10 + div_int [9:0] $end
$var wire 1 , rst_n $end
$var wire 1 - rx $end
$var wire 8 . rx_byte [7:0] $end
$var wire 1 / tx_done $end
$var wire 1 0 tx $end
$var wire 1 1 rx_valid $end
$var wire 1 2 rx_irq $end
$var wire 1 3 rst_n_sync $end
$var wire 1 4 read_reg $end
$var reg 3 5 addr [2:0] $end
$var reg 3 6 cnt_byte [2:0] $end
$var reg 1 7 rx_ren $end
$var reg 4 8 state [3:0] $end
$var reg 32 9 temp_wdata [31:0] $end
$var reg 8 : tx_byte [7:0] $end
$var reg 1 ; tx_valid $end
$scope module inst_reset_sync $end
$var wire 1 ) clk $end
$var wire 1 , rst_n_in $end
$var wire 1 3 rst_n_out $end
$var reg 2 < delay [1:0] $end
$upscope $end
$scope module inst_uart $end
$var wire 1 ) clk $end
$var wire 1 = din $end
$var wire 4 > div_frac [3:0] $end
$var wire 10 ? div_int [9:0] $end
$var wire 1 , rst_n $end
$var wire 1 - rx $end
$var wire 8 @ rx_byte [7:0] $end
$var wire 1 7 rxfifo_ren_ext $end
$var wire 8 A tx_byte [7:0] $end
$var wire 1 B tx_fifo_ren $end
$var wire 8 C tx_fifo_wdata [7:0] $end
$var wire 1 D tx_fifo_wen $end
$var wire 1 ; tx_valid $end
$var wire 8 E tx_fifo_rdata [7:0] $end
$var wire 3 F tx_fifo_lvl [2:0] $end
$var wire 1 G tx_fifo_full $end
$var wire 1 H tx_fifo_empty $end
$var wire 1 / tx_done $end
$var wire 1 I tx_busy $end
$var wire 1 1 rx_valid $end
$var wire 1 J rx_sync $end
$var wire 1 2 rx_irq $end
$var wire 3 K rx_fifo_lvl [2:0] $end
$var wire 1 L rx_fifo_full $end
$var wire 1 M rx_fifo_empty $end
$var wire 1 N rst_n_sync $end
$var wire 1 O clk_en $end
$var reg 2 P rx_over_ctr [1:0] $end
$var reg 8 Q rx_shifter [7:0] $end
$var reg 4 R rx_state [3:0] $end
$var reg 1 S rxfifo_wen $end
$var reg 1 0 tx $end
$var reg 2 T tx_over_ctr [1:0] $end
$var reg 8 U tx_shifter [7:0] $end
$var reg 4 V tx_state [3:0] $end
$scope module inst_clk_div $end
$var wire 1 ) clk $end
$var wire 4 W div_frac [3:0] $end
$var wire 10 X div_int [9:0] $end
$var wire 1 Y en $end
$var wire 1 N rst_n $end
$var reg 1 O clk_en $end
$var reg 4 Z ctr_frac [3:0] $end
$var reg 10 [ ctr_int [9:0] $end
$var reg 1 \ frac_carry $end
$upscope $end
$scope module inst_reset_sync $end
$var wire 1 ) clk $end
$var wire 1 , rst_n_in $end
$var wire 1 N rst_n_out $end
$var reg 2 ] delay [1:0] $end
$upscope $end
$scope module inst_rx_fifo $end
$var wire 1 ) clk $end
$var wire 1 ^ pop $end
$var wire 1 _ push $end
$var wire 8 ` r_data [7:0] $end
$var wire 1 7 r_en $end
$var wire 1 N rst_n $end
$var wire 8 a w_data [7:0] $end
$var wire 1 S w_en $end
$var wire 1 L full $end
$var wire 1 M empty $end
$var reg 3 b level [2:0] $end
$var reg 6 c valid [5:0] $end
$scope begin shift_data $end
$var integer 32 d i [31:0] $end
$scope begin data_stage $end
$upscope $end
$upscope $end
$upscope $end
$scope module inst_sync_rx $end
$var wire 1 ) clk $end
$var wire 1 - i $end
$var wire 1 N rst_n $end
$var wire 1 J o $end
$var reg 2 e sync_flops [1:0] $end
$upscope $end
$scope module inst_tx_fifo $end
$var wire 1 ) clk $end
$var wire 1 f pop $end
$var wire 1 g push $end
$var wire 8 h r_data [7:0] $end
$var wire 1 B r_en $end
$var wire 1 N rst_n $end
$var wire 8 i w_data [7:0] $end
$var wire 1 D w_en $end
$var wire 1 G full $end
$var wire 1 H empty $end
$var reg 3 j level [2:0] $end
$var reg 6 k valid [5:0] $end
$scope begin shift_data $end
$var integer 32 l i [31:0] $end
$scope begin data_stage $end
$upscope $end
$upscope $end
$upscope $end
$upscope $end
$scope begin $unm_blk_54 $end
$var integer 32 m i [31:0] $end
$upscope $end
$upscope $end
$enddefinitions $end
#0
$dumpvars
b1000 m
b101 l
b0 k
b0 j
b0 i
bx h
0g
0f
b11 e
b101 d
b0 c
b0 b
b0 a
bx `
0_
0^
b0 ]
0\
b1 [
b0 Z
1Y
b10 X
b0 W
b0 V
b0 U
b0 T
0S
b0 R
b0 Q
b0 P
0O
0N
1M
0L
b0 K
1J
0I
1H
0G
b0 F
bx E
0D
b0 C
0B
b0 A
bx @
b10 ?
b0 >
1=
b0 <
0;
b0 :
b0 9
b0 8
07
b0 6
b0 5
x4
03
02
01
10
0/
bx .
1-
0,
b10 +
b0 *
1)
bz (
bz '
bz &
bz %
bz $
bz #
bz "
bz !
$end
#50000
0)
#100000
1,
b101 d
b101 l
1)
#150000
0)
#200000
b1 <
b1 ]
b101 d
b101 l
1)
#250000
0)
#300000
1N
13
b11 ]
b11 <
b101 d
b101 l
1)
#350000
0)
#400000
0-
1O
b10 [
b101 d
b101 l
1)
#450000
0)
#500000
b10 e
b1 [
0O
0I
b0 V
b0 T
b0 R
b0 P
b101 d
b101 l
1)
#550000
0)
#600000
0=
0J
1O
b10 [
b0 e
b101 d
b101 l
1)
#650000
0)
#700000
b1 [
0O
0I
b0 V
b0 T
b1 R
b1 P
b101 d
b101 l
1)
#750000
0)
#800000
1O
b10 [
b101 d
b101 l
1)
#850000
0)
#900000
b1 [
0O
0I
b0 V
b0 T
b10 P
b101 d
b101 l
1)
#950000
0)
#1000000
1O
b10 [
b101 d
b101 l
1)
#1050000
0)
#1100000
b1 [
0O
0I
b0 V
b0 T
b11 P
b101 d
b101 l
1)
#1150000
0)
#1200000
1O
b10 [
b1 e
b101 d
b101 l
1)
1-
#1250000
0)
#1300000
1=
1J
b11 e
b1 [
0O
0I
b0 V
b0 T
b0 P
b101 d
b101 l
1)
#1350000
0)
#1400000
1O
b10 [
b101 d
b101 l
1)
#1450000
0)
#1500000
b1 [
0O
0I
b0 V
b0 T
b10 R
b10 P
b101 d
b101 l
1)
#1550000
0)
#1600000
1O
b10 [
b101 d
b101 l
1)
#1650000
0)
#1700000
b1 [
0O
0I
b0 V
b0 T
b11 P
b101 d
b101 l
1)
#1750000
0)
#1800000
1O
b10 [
b101 d
b101 l
1)
#1850000
0)
#1900000
b1 [
0O
0I
b0 V
b0 T
b0 P
b101 d
b101 l
1)
#1950000
0)
#2000000
1O
b10 [
b101 d
b101 l
1)
#2050000
0)
#2100000
b1 [
0O
0I
b0 V
b0 T
b10000000 Q
b10000000 a
b11 R
b1 P
b101 d
b101 l
1)
#2150000
0)
#2200000
1O
b10 [
b101 d
b101 l
1)
#2250000
0)
#2300000
b1 [
0O
0I
b0 V
b0 T
b10 P
b101 d
b101 l
1)
#2350000
0)
#2400000
1O
b10 [
b101 d
b101 l
1)
#2450000
0)
#2500000
b1 [
0O
0I
b0 V
b0 T
b11 P
b101 d
b101 l
1)
#2550000
0)
#2600000
1O
b10 [
b101 d
b101 l
1)
#2650000
0)
#2700000
b1 [
0O
0I
b0 V
b0 T
b0 P
b101 d
b101 l
1)
#2750000
0)
#2800000
1O
b10 [
b101 d
b101 l
1)
#2850000
0)
#2900000
b1 [
0O
0I
b0 V
b0 T
b11000000 Q
b11000000 a
b100 R
b1 P
b101 d
b101 l
1)
#2950000
0)
#3000000
1O
b10 [
b101 d
b101 l
1)
#3050000
0)
#3100000
b1 [
0O
0I
b0 V
b0 T
b10 P
b101 d
b101 l
1)
#3150000
0)
#3200000
1O
b10 [
b101 d
b101 l
1)
#3250000
0)
#3300000
b1 [
0O
0I
b0 V
b0 T
b11 P
b101 d
b101 l
1)
#3350000
0)
#3400000
1O
b10 [
b101 d
b101 l
1)
#3450000
0)
#3500000
b1 [
0O
0I
b0 V
b0 T
b0 P
b101 d
b101 l
1)
#3550000
0)
#3600000
1O
b10 [
b10 e
b101 d
b101 l
1)
0-
#3650000
0)
#3700000
0=
0J
b0 e
b1 [
0O
0I
b0 V
b0 T
b11100000 Q
b11100000 a
b101 R
b1 P
b101 d
b101 l
1)
#3750000
0)
#3800000
1O
b10 [
b101 d
b101 l
1)
#3850000
0)
#3900000
b1 [
0O
0I
b0 V
b0 T
b10 P
b101 d
b101 l
1)
#3950000
0)
#4000000
1O
b10 [
b101 d
b101 l
1)
#4050000
0)
#4100000
b1 [
0O
0I
b0 V
b0 T
b11 P
b101 d
b101 l
1)
#4150000
0)
#4200000
1O
b10 [
b101 d
b101 l
1)
#4250000
0)
#4300000
b1 [
0O
0I
b0 V
b0 T
b0 P
b101 d
b101 l
1)
#4350000
0)
#4400000
1O
b10 [
b101 d
b101 l
1)
#4450000
0)
#4500000
b1 [
0O
0I
b0 V
b0 T
b1110000 Q
b1110000 a
b110 R
b1 P
b101 d
b101 l
1)
#4550000
0)
#4600000
1O
b10 [
b101 d
b101 l
1)
#4650000
0)
#4700000
b1 [
0O
0I
b0 V
b0 T
b10 P
b101 d
b101 l
1)
#4750000
0)
#4800000
1O
b10 [
b101 d
b101 l
1)
#4850000
0)
#4900000
b1 [
0O
0I
b0 V
b0 T
b11 P
b101 d
b101 l
1)
#4950000
0)
#5000000
1O
b10 [
b101 d
b101 l
1)
#5050000
0)
#5100000
b1 [
0O
0I
b0 V
b0 T
b0 P
b101 d
b101 l
1)
#5150000
0)
#5200000
1O
b10 [
b1 e
b101 d
b101 l
1)
1-
#5250000
0)
#5300000
1=
1J
b11 e
b1 [
0O
0I
b0 V
b0 T
b111000 Q
b111000 a
b111 R
b1 P
b101 d
b101 l
1)
#5350000
0)
#5400000
1O
b10 [
b101 d
b101 l
1)
#5450000
0)
#5500000
b1 [
0O
0I
b0 V
b0 T
b10 P
b101 d
b101 l
1)
#5550000
0)
#5600000
1O
b10 [
b101 d
b101 l
1)
#5650000
0)
#5700000
b1 [
0O
0I
b0 V
b0 T
b11 P
b101 d
b101 l
1)
#5750000
0)
#5800000
1O
b10 [
b101 d
b101 l
1)
#5850000
0)
#5900000
b1 [
0O
0I
b0 V
b0 T
b0 P
b101 d
b101 l
1)
#5950000
0)
#6000000
1O
b10 [
b10 e
b101 d
b101 l
1)
0-
#6050000
0)
#6100000
0=
0J
b0 e
b1 [
0O
0I
b0 V
b0 T
b10011100 Q
b10011100 a
b1000 R
b1 P
b101 d
b101 l
1)
#6150000
0)
#6200000
1O
b10 [
b101 d
b101 l
1)
#6250000
0)
#6300000
b1 [
0O
0I
b0 V
b0 T
b10 P
b101 d
b101 l
1)
#6350000
0)
#6400000
1O
b10 [
b101 d
b101 l
1)
#6450000
0)
#6500000
b1 [
0O
0I
b0 V
b0 T
b11 P
b101 d
b101 l
1)
#6550000
0)
#6600000
1O
b10 [
b101 d
b101 l
1)
#6650000
0)
#6700000
b1 [
0O
0I
b0 V
b0 T
b0 P
b101 d
b101 l
1)
#6750000
0)
#6800000
1O
b10 [
b1 e
b101 d
b101 l
1)
1-
#6850000
0)
#6900000
1=
1J
b11 e
b1 [
0O
0I
b0 V
b0 T
b1001110 Q
b1001110 a
b1001 R
b1 P
b101 d
b101 l
1)
#6950000
0)
#7000000
1O
b10 [
b101 d
b101 l
1)
#7050000
0)
#7100000
b1 [
0O
0I
b0 V
b0 T
b10 P
b101 d
b101 l
1)
#7150000
0)
#7200000
1O
b10 [
b101 d
b101 l
1)
#7250000
0)
#7300000
b1 [
0O
0I
b0 V
b0 T
b11 P
b101 d
b101 l
1)
#7350000
0)
#7400000
1O
b10 [
b101 d
b101 l
1)
#7450000
0)
#7500000
b1 [
0O
0I
b0 V
b0 T
b0 P
b101 d
b101 l
1)
#7550000
0)
#7600000
1O
b10 [
b101 d
b101 l
1)
#7650000
0)
#7700000
b1 [
0O
0I
b0 V
b0 T
b10100111 Q
b10100111 a
11
b1010 R
b1 P
b101 d
b101 l
1)
#7750000
0)
#7800000
1O
b10 [
b101 d
b101 l
1)
#7850000
0)
#7900000
b1 [
0O
0I
b0 V
b0 T
b10 P
b101 d
b101 l
1)
#7950000
0)
#8000000
1O
b10 [
b101 d
b101 l
1)
#8050000
0)
#8100000
b1 [
0O
0I
b0 V
b0 T
b11 P
b101 d
b101 l
1)
#8150000
0)
#8200000
1O
b10 [
b101 d
b101 l
1)
#8250000
0)
#8300000
b1 [
0O
0I
b0 V
b0 T
b0 P
b101 d
b101 l
1)
#8350000
0)
#8400000
1O
b10 [
b101 d
b101 l
1)
#8450000
0)
#8500000
1_
b1 [
0O
0I
b0 V
b0 T
1S
01
b0 R
b0 P
b101 d
b101 l
1)
#8550000
0)
#8600000
0_
12
0M
14
0S
b1 K
b1 b
b1 c
1O
b10 [
b10100111 .
b10100111 @
b10100111 `
b101 d
b101 l
1)
#8650000
0)
#8700000
1^
b1 [
0O
0I
b0 V
b0 T
b0 R
b0 P
b1 8
b111 5
17
b101 d
b101 l
1)
#8750000
0)
#8800000
02
1M
1g
0^
b0 K
b0 b
b0 c
1O
b10 [
b1111000 C
b1111000 i
b1111000 :
b1111000 A
1D
1;
b1 6
07
b101 d
b101 l
1)
#8850000
0)
#8900000
0H
b1 [
0O
b1 k
b1 F
b1 j
0I
b0 V
b0 T
b0 R
b0 P
b1111000 E
b1111000 h
b1010110 C
b1010110 i
b1010110 :
b1010110 A
b10 6
b101 d
b101 l
1)
#8950000
0)
#9000000
1f
1B
b10 F
b10 j
b11 k
1O
b10 [
b110100 C
b110100 i
b110100 :
b110100 A
b11 6
b101 d
b101 l
1)
#9050000
0)
#9100000
0f
0B
b1 [
0O
00
b1111000 U
1I
b1 V
b1 T
b0 R
b0 P
b1010110 E
b1010110 h
b0 8
b10010 C
b10010 i
b10010 :
b10010 A
b0 6
b101 d
b101 l
1)
#9150000
0)
#9200000
0g
b11 F
b11 j
b111 k
1O
b10 [
0D
0;
b101 d
b101 l
1)
#9250000
0)
#9300000
b1 [
0O
b10 T
b0 R
b0 P
b101 d
b101 l
1)
#9350000
0)
#9400000
1O
b10 [
b101 d
b101 l
1)
#9450000
0)
#9500000
b1 [
0O
b11 T
b0 R
b0 P
b101 d
b101 l
1)
#9550000
0)
#9600000
1O
b10 [
b101 d
b101 l
1)
#9650000
0)
#9700000
b1 [
0O
b0 T
b0 R
b0 P
b101 d
b101 l
1)
#9750000
0)
#9800000
1O
b10 [
b101 d
b101 l
1)
#9850000
0)
#9900000
b1 [
0O
b111100 U
b10 V
b1 T
b0 R
b0 P
b101 d
b101 l
1)
#9950000
0)
#10000000
1O
b10 [
b101 d
b101 l
1)
#10050000
0)
#10100000
b1 [
0O
b10 T
b0 R
b0 P
b101 d
b101 l
1)
#10150000
0)
#10200000
1O
b10 [
b101 d
b101 l
1)
#10250000
0)
#10300000
b1 [
0O
b11 T
b0 R
b0 P
b101 d
b101 l
1)
#10350000
0)
#10400000
1O
b10 [
b101 d
b101 l
1)
#10450000
0)
#10500000
b1 [
0O
b0 T
b0 R
b0 P
b101 d
b101 l
1)
#10550000
0)
#10600000
1O
b10 [
b101 d
b101 l
1)
#10650000
0)
#10700000
b1 [
0O
b11110 U
b11 V
b1 T
b0 R
b0 P
b101 d
b101 l
1)
#10750000
0)
#10800000
1O
b10 [
b101 d
b101 l
1)
#10850000
0)
#10900000
b1 [
0O
b10 T
b0 R
b0 P
b101 d
b101 l
1)
#10950000
0)
#11000000
1O
b10 [
b101 d
b101 l
1)
#11050000
0)
#11100000
b1 [
0O
b11 T
b0 R
b0 P
b101 d
b101 l
1)
#11150000
0)
#11200000
1O
b10 [
b101 d
b101 l
1)
#11250000
0)
#11300000
b1 [
0O
b0 T
b0 R
b0 P
b101 d
b101 l
1)
#11350000
0)
#11400000
1O
b10 [
b101 d
b101 l
1)
#11450000
0)
#11500000
b1 [
0O
b1111 U
b100 V
b1 T
b0 R
b0 P
b101 d
b101 l
1)
#11550000
0)
#11600000
1O
b10 [
b101 d
b101 l
1)
#11650000
0)
#11700000
b1 [
0O
b10 T
b0 R
b0 P
b101 d
b101 l
1)
#11750000
0)
#11800000
1O
b10 [
b101 d
b101 l
1)
#11850000
0)
#11900000
b1 [
0O
b11 T
b0 R
b0 P
b101 d
b101 l
1)
#11950000
0)
#12000000
1O
b10 [
b101 d
b101 l
1)
#12050000
0)
#12100000
b1 [
0O
b0 T
b0 R
b0 P
b101 d
b101 l
1)
#12150000
0)
#12200000
1O
b10 [
b101 d
b101 l
1)
#12250000
0)
#12300000
b1 [
0O
10
b111 U
b101 V
b1 T
b0 R
b0 P
b101 d
b101 l
1)
#12350000
0)
#12400000
1O
b10 [
b101 d
b101 l
1)
#12450000
0)
#12500000
b1 [
0O
b10 T
b0 R
b0 P
b101 d
b101 l
1)
#12550000
0)
